py_qvalue/__init__.py
py_qvalue/core.py
py_qvalue-0.1.1.dist-info/LICENSE
py_qvalue-0.1.1.dist-info/METADATA
py_qvalue-0.1.1.dist-info/WHEEL
py_qvalue-0.1.1.dist-info/RECORD
