Metadata-Version: 2.3
Name: py-qvalue
Version: 0.1.1
Summary: A Python package providing ports of statistical methods originally implemented in R.
License: GPL-3.0-or-later
Keywords: statistics,q-value,biostatistics,R ports,FDR
Author: Kynon J.M. Benjamin
Author-email: kj.benjamin90@gmail.com
Maintainer: Kynon J.M. Benjamin
Maintainer-email: kj.benjamin90@gmail.com
Requires-Python: >=3.10
Classifier: License :: OSI Approved :: GNU General Public License v3 or later (GPLv3+)
Classifier: Programming Language :: Python :: 3
Classifier: Programming Language :: Python :: 3.10
Classifier: Programming Language :: Python :: 3.11
Classifier: Programming Language :: Python :: 3.12
Classifier: Programming Language :: Python :: 3.13
Requires-Dist: numpy (>=2.0)
Requires-Dist: scipy (>=1.15)
Project-URL: Bug Tracker, https://github.com/heart-gen/py-qvalue/issues
Project-URL: Homepage, https://github.com/heart-gen/py-qvalue
Project-URL: Repository, https://github.com/heart-gen/py-qvalue
